agenttrace/__init__.py
agenttrace/client.py
agenttrace/decorators.py
agenttrace_sdk-1.0.0.dist-info/licenses/LICENSE
agenttrace_sdk-1.0.0.dist-info/METADATA
agenttrace_sdk-1.0.0.dist-info/WHEEL
agenttrace_sdk-1.0.0.dist-info/top_level.txt
agenttrace_sdk-1.0.0.dist-info/RECORD
