Metadata-Version: 2.4
Name: agenttrace-sdk
Version: 1.0.0
Summary: AgentTrace SDK - AI Agent Observability & Debugging
Home-page: https://agenttrace.io
Author: AgentTrace Team
Author-email: AgentTrace Team <agenttraceismoat@gmail.com>
License: MIT
Project-URL: Homepage, https://agenttrace.io
Project-URL: Documentation, https://docs.agenttrace.io
Project-URL: Repository, https://github.com/agenttrace/sdk
Keywords: ai,agent,tracing,debugging,observability,llm,openai,langchain
Classifier: Development Status :: 4 - Beta
Classifier: Intended Audience :: Developers
Classifier: License :: OSI Approved :: MIT License
Classifier: Operating System :: OS Independent
Classifier: Programming Language :: Python :: 3
Classifier: Programming Language :: Python :: 3.8
Classifier: Programming Language :: Python :: 3.9
Classifier: Programming Language :: Python :: 3.10
Classifier: Programming Language :: Python :: 3.11
Classifier: Programming Language :: Python :: 3.12
Classifier: Topic :: Software Development :: Debuggers
Classifier: Topic :: System :: Monitoring
Requires-Python: >=3.8
License-File: LICENSE
Requires-Dist: requests>=2.25.0
Provides-Extra: openai
Requires-Dist: openai>=1.0.0; extra == "openai"
Provides-Extra: langchain
Requires-Dist: langchain>=0.1.0; extra == "langchain"
Dynamic: author
Dynamic: home-page
Dynamic: license-file
Dynamic: requires-python
